{
	"format_version": "1.8.0",
	"animations": {
		"animation.vzombie.walk": {
			"loop": true,
			"animation_length": 1,
			"bones": {
				"armright": {
					"rotation": {
						"0.0": {
							"vector": [0, 0, 0]
						},
						"0.25": {
							"vector": [-19, 0, 0]
						},
						"0.5": {
							"vector": [0, 0, 0]
						},
						"0.75": {
							"vector": [20, 0, 0]
						},
						"1.0": {
							"vector": [0, 0, 0]
						}
					}
				},
				"armleft": {
					"rotation": {
						"0.0": {
							"vector": [0, 0, 0]
						},
						"0.25": {
							"vector": [15, 0, 0]
						},
						"0.5": {
							"vector": [0, 0, 0]
						},
						"0.75": {
							"vector": [-19, 0, 0]
						},
						"1.0": {
							"vector": [0, 0, 0]
						}
					}
				},
				"RightLeg": {
					"rotation": {
						"0.0": {
							"vector": [0, 0, 0]
						},
						"0.25": {
							"vector": [-19, 0, 0]
						},
						"0.5": {
							"vector": [0, 0, 0]
						},
						"0.75": {
							"vector": [16, 0, 0]
						},
						"1.0": {
							"vector": [0, 0, 0]
						}
					}
				},
				"LeftLeg": {
					"rotation": {
						"0.0": {
							"vector": [0, 0, 0]
						},
						"0.25": {
							"vector": [16, 0, 0]
						},
						"0.5": {
							"vector": [0, 0, 0]
						},
						"0.75": {
							"vector": [-19, 0, 0]
						},
						"1.0": {
							"vector": [0, 0, 0]
						}
					}
				},
				"upperbody": {
					"rotation": {
						"0.0": {
							"vector": [0, 0, 0]
						},
						"0.125": {
							"vector": [-1, 0, 0]
						},
						"0.25": {
							"vector": [0, 0, 0]
						},
						"0.375": {
							"vector": [1, 0, 0]
						},
						"0.5": {
							"vector": [0, 0, 0]
						},
						"0.625": {
							"vector": [-1, 0, 0]
						},
						"0.75": {
							"vector": [0, 0, 0]
						},
						"0.875": {
							"vector": [1, 0, 0]
						},
						"1.0": {
							"vector": [0, 0, 0]
						}
					}
				}
			}
		},
		"animation.vzombie.idle": {
			"loop": true,
			"animation_length": 0.79167,
			"bones": {
				"armright": {
					"rotation": {
						"0.0": {
							"vector": [0, 0, 0]
						},
						"0.25": {
							"vector": [-15.40765, -2.0957, -9.12158]
						},
						"0.5": {
							"vector": [0, 0, 0]
						}
					}
				},
				"armleft": {
					"rotation": {
						"0.0": {
							"vector": [0, 0, 0]
						},
						"0.25": {
							"vector": [-7.62135, 1.44719, 5.57248]
						},
						"0.5": {
							"vector": [0, 0, 0]
						}
					}
				}
			}
		},
		"animation.vzombie.attack": {
			"animation_length": 0.66667,
			"bones": {
				"armright": {
					"rotation": {
						"0.0": {
							"vector": [0, 0, 0]
						},
						"0.25": {
							"vector": [-11, 0, 0]
						},
						"0.375": {
							"vector": [-11, 0, 0]
						},
						"0.5417": {
							"vector": [23, 0, 0]
						},
						"0.6667": {
							"vector": [0, 0, 0]
						}
					}
				},
				"armleft": {
					"rotation": {
						"0.0": {
							"vector": [0, 0, 0]
						},
						"0.25": {
							"vector": [2.99775, 30.86909, 28.82784]
						},
						"0.375": {
							"vector": [2.99775, 30.86909, 28.82784]
						},
						"0.4167": {
							"vector": [-61.80145, 0.46329, 7.10008]
						},
						"0.4583": {
							"vector": [-68.60064, -29.94251, -14.62767]
						},
						"0.5417": {
							"vector": [-68.60064, -29.94251, -14.62767]
						},
						"0.6667": {
							"vector": [0, 0, 0]
						}
					}
				},
				"upperbody": {
					"rotation": {
						"0.0": {
							"vector": [0, 0, 0]
						},
						"0.25": {
							"vector": [0, 21.5, 0]
						},
						"0.375": {
							"vector": [0, 21.5, 0]
						},
						"0.4583": {
							"vector": [0, -11.5, 0]
						},
						"0.5417": {
							"vector": [0, -11.5, 0]
						},
						"0.6667": {
							"vector": [0, 0, 0]
						}
					}
				}
			}
		},
		"animation.vzombie.attack2": {
			"animation_length": 0.66667,
			"bones": {
				"armright": {
					"rotation": {
						"0.0": {
							"vector": [0, 0, 0]
						},
						"0.2083": {
							"vector": [-32.26692, -34.21432, -12.42474]
						},
						"0.3333": {
							"vector": [-44.37028, -50.85281, 5.21613]
						},
						"0.4167": {
							"vector": [-61.5365, 7.50765, 10.90341]
						},
						"0.4583": {
							"vector": [-72.40087, 20.20638, 3.1704]
						},
						"0.5417": {
							"vector": [-72.40087, 20.20638, 3.1704]
						},
						"0.6667": {
							"vector": [0, 0, 0]
						}
					}
				},
				"armleft": {
					"rotation": {
						"0.0": {
							"vector": [0, 0, 0]
						},
						"0.25": {
							"vector": [-18, 0, 0]
						},
						"0.375": {
							"vector": [-18, 0, 0]
						},
						"0.5417": {
							"vector": [22.79915, -3.11724, 7.37133]
						},
						"0.6667": {
							"vector": [0, 0, 0]
						}
					}
				},
				"upperbody": {
					"rotation": {
						"0.0": {
							"vector": [0, 0, 0]
						},
						"0.25": {
							"vector": [0, -34.5, 0]
						},
						"0.375": {
							"vector": [0, -38.5, 0]
						},
						"0.4583": {
							"vector": [0, 20.5, 0]
						},
						"0.5417": {
							"vector": [0, 20.5, 0]
						},
						"0.6667": {
							"vector": [0, 0, 0]
						}
					}
				}
			}
		},
		"animation.vzombie.attack3": {
			"animation_length": 0.66667,
			"bones": {
				"armright": {
					"rotation": {
						"0.0": {
							"vector": [0, 0, 0]
						},
						"0.25": {
							"vector": [-153.50874, -5.41621, 10.72419]
						},
						"0.3333": {
							"vector": [-153.50874, -5.41621, 10.72419]
						},
						"0.4167": {
							"vector": [-59.64385, -0.59876, 20.58564]
						},
						"0.4583": {
							"vector": [-59.64385, -0.59876, 20.58564]
						},
						"0.6667": {
							"vector": [0, 0, 0]
						}
					}
				},
				"armleft": {
					"rotation": {
						"0.0": {
							"vector": [0, 0, 0]
						},
						"0.25": {
							"vector": [-158.14849, 2.61664, -6.49481]
						},
						"0.3333": {
							"vector": [-158.14849, 2.61664, -6.49481]
						},
						"0.4167": {
							"vector": [-46.38123, -4.26048, -16.29284]
						},
						"0.4583": {
							"vector": [-46.38123, -4.26048, -16.29284]
						},
						"0.6667": {
							"vector": [0, 0, 0]
						}
					}
				},
				"upperbody": {
					"rotation": {
						"0.0": {
							"vector": [0, 0, 0]
						},
						"0.25": {
							"vector": [-6, 0, 0]
						},
						"0.3333": {
							"vector": [-6, 0, 0]
						},
						"0.4167": {
							"vector": [13.5, 0, 0]
						},
						"0.4583": {
							"vector": [13.5, 0, 0]
						},
						"0.6667": {
							"vector": [0, 0, 0]
						}
					}
				}
			}
		}
	},
	"geckolib_format_version": 2
}